recursiveseriation/__init__.py
recursiveseriation/exc.py
recursiveseriation/logger.py
recursiveseriation/settings.py
recursiveseriation/solver/__init__.py
recursiveseriation/solver/neighbours_graph.py
recursiveseriation/solver/qtree.py
recursiveseriation/solver/seriation.py
recursiveseriation/utils.py
recursiveseriation-0.1.2.dist-info/LICENSE
recursiveseriation-0.1.2.dist-info/METADATA
recursiveseriation-0.1.2.dist-info/WHEEL
recursiveseriation-0.1.2.dist-info/RECORD
